src/chip8_display.v
`timescale 1ns / 1ps

module chip8_display(
    input wire clk,
    input wire reset,
    input wire draw,
    input wire [5:0] x,
    input wire [4:0] y,
    input wire [3:0] row_index,
    input wire [7:0] sprite_data,
    input wire [2047:0] display_in,
    output reg  [2047:0] display_out,
    output reg collision
    );
    
    reg [2047:0] next_display;
    reg collide;
    integer i;
    integer index;
    
    always @(*) begin
        
        collide = 0;
        next_display = display_in;
        
        for (i = 0;i<8;i=i+1) begin
        if (sprite_data[7-i]) begin
                index = ((y + row_index) % 32) * 64 + ((x + i) % 64);
            
                if (display_in[index])
                        collide = 1;
                         
                next_display[index] = display_in[index] ^ 1'b1;
            end
        end
    end
    
    always @(posedge clk) begin
        if (reset) {display_out, collision} <= 0;
        else if (draw) begin
            display_out <= next_display;
            collision <= collide;
        end
    end
endmodule

src/chip8_mem.v
`timescale 1ns / 1ps

module chip8_mem(
    input wire clk,
    input wire write,
    input wire read,
    input wire [7:0] mem_data_in,
    input wire [11:0] mem_address,
    output reg [7:0] mem_data_out
    );

    // This memory will be inferred as a Block RAM (BRAM) on an FPGA.
    // To initialize this memory on hardware, you would typically use a
    // memory initialization file (.mif or .coe) specified in your
    // FPGA project settings, or use a synthesis directive.
    reg [7:0] memory[0:4095];

    // The font set needs to be loaded into the BRAM during initialization.
    // For simulation, we can still use an initial block. For synthesis,
    // this block should be wrapped in a `ifdef SIMULATION` guard or
    // be handled by vendor-specific memory initialization.
    initial begin
        memory[0] = 8'hF0; memory[1] = 8'h90; memory[2] = 8'h90; memory[3] = 8'h90; memory[4] = 8'hF0; // 0
        memory[5] = 8'h20; memory[6] = 8'h60; memory[7] = 8'h20; memory[8] = 8'h20; memory[9] = 8'h70; // 1
        // ... (rest of the font set)
        $readmemh("src/game.mem", memory, 512);
    end

    always @(posedge clk) begin
        if (write) begin
            memory[mem_address] <= mem_data_in;
        end
        // The read is registered, data will be available on the next clock cycle
        mem_data_out <= memory[mem_address];
    end

endmodule

src/chip8_cpu.v
`timescale 1ns / 1ps

module chip8_cpu (
    input wire clk,
    input wire reset,
    input wire [7:0] mem_data_out,
    input wire [15:0] key_pressed,
    input wire collision,

    output reg mem_read,
    output reg [11:0] mem_addr_out,
    output reg [7:0] mem_data_in,
    output reg mem_write,
    output reg draw,
    output reg [5:0] x,
    output reg [4:0] y,
    output reg [7:0] sprite_data,
    output reg [3:0] draw_row_index
);
    reg [11:0]    pc;
    reg [11:0]    I;
    reg [7:0]     V[0:15];
    reg [15:0]    opcode;
    reg [3:0]     state;
    reg [3:0]     pc_data;
    reg [11:0]    stack[0:15];
    reg [7:0]     opcode_fh;
    reg [7:0]     opcode_sh;
    reg [7:0]     delay_timer,sound_timer;
    reg [20:0]    one_hz;
    reg [3:0]     i;
    reg [3:0]     draw_row;
    reg [15:0]    lfsr; // Pseudo-random number generator

    localparam FETCH1 = 0;
    localparam FETCH1_WAIT = 1;
    localparam FETCH2 = 2;
    localparam FETCH2_WAIT = 3;
    localparam LASTFETCH = 4;
    localparam EXECUTE = 5;
    localparam LASTFETCH_WAIT = 6;
    localparam STORE = 7;
    localparam RETRIEVE = 8;
    localparam RETRIEVE_WAIT = 9;
    localparam DRAW_START = 10;
    localparam DRAW_INC = 11;
    localparam DRAW_FETCH = 12;

    always @(posedge clk or posedge reset) begin
        if(reset) begin
            pc <= 12'h200;
            state <= FETCH1;
            opcode <= 0;
            I <= 12'd0;
            opcode_fh <= 0;
            opcode_sh <= 0;
            mem_read <= 0;
            mem_write <= 0;
            delay_timer <= 0;
            pc_data <= 0;
            one_hz <= 0;
            sound_timer <= 0;
            draw <= 0;
            draw_row <= 0;
            draw_row_index <= 0;
            sprite_data <= 8'd0;
            lfsr <= 16'hACE1; // LFSR seed
        end else begin
            if (one_hz == 833333) begin
                one_hz <= 0;
                if (delay_timer > 0)
                    delay_timer <= delay_timer - 1;
                if (sound_timer > 0)
                    sound_timer <= sound_timer - 1;
            end else begin
                one_hz <= one_hz + 1;
            end

            // Update LFSR for random number generation
            lfsr <= {lfsr[14:0], lfsr[15] ^ lfsr[5] ^ lfsr[4] ^ lfsr[2]};

            if (collision) begin
                V[15] <= 1;
            end

            mem_read <= 0;
            mem_write <= 0;

            case(state)
            FETCH1: begin
                mem_addr_out <= pc;
                mem_read <= 1;
                state <= FETCH1_WAIT;
            end

            FETCH1_WAIT: begin
                state <= FETCH2;
            end

            FETCH2: begin
                opcode_fh <= mem_data_out;
                mem_addr_out <= pc + 1;
                mem_read <= 1;
                state <= FETCH2_WAIT;
            end

            FETCH2_WAIT: begin
                state <= LASTFETCH;
            end

            LASTFETCH: begin
                opcode_sh <= mem_data_out;
                state <= LASTFETCH_WAIT;
            end

            LASTFETCH_WAIT: begin
                opcode <= {opcode_fh, opcode_sh};
                state <= EXECUTE;
            end

            EXECUTE: begin
                case(opcode[15:12])
                    4'h6: begin
                        V[opcode[11:8]] <= opcode[7:0];
                        pc <= pc + 2;
                        state <= FETCH1;
                    end

                    4'h7: begin
                        V[opcode[11:8]] <= V[opcode[11:8]] + opcode[7:0];
                        pc <= pc + 2;
                        state <= FETCH1;
                    end

                    4'h1: begin
                        pc <= opcode[11:0];
                        state <= FETCH1;
                    end

                    4'h2: begin
                        stack[pc_data] <= pc + 2;
                        pc <= opcode[11:0];
                        pc_data <= pc_data + 1;
                        state <= FETCH1;
                    end

                    4'hC: begin
                        V[opcode[11:8]] <= opcode[7:0] & lfsr[7:0]; // Use LFSR
                        pc <= pc + 2;
                        state <= FETCH1;
                    end
                    
                    // ... (rest of the EXECUTE case statements are unchanged)
                    
                    4'hD: begin
                        draw_row <= 0;
                        draw_row_index <= 0;
                        mem_read <= 1;
                        mem_addr_out <= I;
                        state <= DRAW_START;
                    end

                    // ... (other cases)
                    default: begin
                        pc <= pc + 2;
                        state <= FETCH1;
                    end
                endcase
            end

            STORE: begin
                mem_addr_out <= I + i;
                mem_data_in <= V[i];
                mem_write <= 1;

                if (i == opcode[11:8]) begin
                    pc <= pc + 2;
                    state <= FETCH1;
                end else begin
                    i <= i+1;
                    state <= STORE;
                end
            end

            RETRIEVE: begin
                if(i <= opcode[11:8]) begin
                    mem_addr_out <= I + i;
                    mem_read <= 1;
                    state <= RETRIEVE_WAIT;
                end
                else begin
                    pc <= pc + 2;
                    state <= FETCH1;
                end
            end

            RETRIEVE_WAIT: begin
              V[i] <= mem_data_out;
              i <= i + 1;
              state <= RETRIEVE;
            end

            DRAW_START: begin
                draw <= 1;
                sprite_data <= mem_data_out;
                x <= V[opcode[11:8]][5:0];
                y <= V[opcode[7:4]][4:0];
                draw_row_index <= draw_row;
                state <= DRAW_INC;
            end

            DRAW_INC: begin
                draw <= 0;
                draw_row <= draw_row + 1;

                if (draw_row == opcode[3:0] - 1) begin
                    pc <= pc + 2;
                    state <= FETCH1;
                end else begin
                    mem_addr_out <= I + draw_row + 1;
                    mem_read <= 1;
                    state <= DRAW_FETCH;
                end
            end

            DRAW_FETCH: begin
                state <= DRAW_START;
            end
        endcase
      end
    end
endmodule

src/chip8_top.v
`timescale 1ns / 1ps

module chip8_top(
    input wire clk,
    input wire reset,
    input wire [15:0] key_pressed,
    output wire [2047:0] display
    );

    wire [7:0] mem_data_in;
    wire [7:0] mem_data_out;
    wire [7:0] sprite_data;
    wire [3:0] draw_row_index;
    wire [5:0] x;
    wire [4:0] y;
    wire [11:0] mem_addr_out;
    wire mem_read, mem_write;
    wire draw;
    wire collision;
    reg [2047:0] display_now;
    wire [2047:0] display_after;

    chip8_cpu cpu (
        .clk(clk),
        .reset(reset),
        .mem_data_out(mem_data_out),
        .key_pressed(key_pressed),
        .collision(collision),
        .mem_read(mem_read),
        .mem_addr_out(mem_addr_out),
        .mem_data_in(mem_data_in),
        .mem_write(mem_write),
        .draw(draw),
        .x(x),
        .y(y),
        .sprite_data(sprite_data),
        .draw_row_index(draw_row_index)
    );

    chip8_mem mem (
        .clk(clk),
        .write(mem_write),
        .read(mem_read),
        .mem_data_in(mem_data_in),
        .mem_data_out(mem_data_out),
        .mem_address(mem_addr_out)
    );

    chip8_display display_module (
        .clk(clk),
        .reset(reset),
        .draw(draw),
        .x(x),
        .y(y),
        .row_index(draw_row_index),
        .sprite_data(sprite_data),
        .display_in(display_now),
        .display_out(display_after),
        .collision(collision)
    );

    always @(posedge clk or posedge reset) begin
        if (reset)
            display_now <= 2048'd0;
        else if (draw)
            display_now <= display_after;
    end

    assign display = display_now;

endmodule

tb/chip8_top_tb.v
`timescale 1ns / 1ps

module chip8_top_testbench();

    reg         clock;
    reg         reset;
    reg  [15:0] key_pressed;
    wire [2047:0] display;
    
    chip8_top DUT (
        .clk(clock),
        .reset(reset),
        .key_pressed(key_pressed),
        .display(display)
    );

    initial clock = 0;
    always #10 clock = ~clock;

    initial begin

        $dumpfile("chip8_top_tb.vcd");
        $dumpvars(0, chip8_top_testbench);
        key_pressed = 16'd0;
        reset = 1;
        
        $monitor("Time=%0t | PC=%h | State=%d | Opcode=%h | I_reg=%h | V0=%h V1=%h VA=%h VB=%h | mem_addr_out=%h | mem_data_in = %h | mem_data_out = %h | mem_read = %h | mem_write = %h",
                 $time,
                 DUT.cpu.pc,           
                 DUT.cpu.state,        
                 DUT.cpu.opcode,       
                 DUT.cpu.I,            
                 DUT.cpu.V[0],         
                 DUT.cpu.V[1],         
                 DUT.cpu.V[10],        
                 DUT.cpu.V[11],         
                 DUT.cpu.mem_addr_out,
                 DUT.cpu.mem_data_in,
                 DUT.cpu.mem_data_out,
                 DUT.cpu.mem_read,
                 DUT.cpu.mem_write
        );
        
        #20;
        reset = 0;
        
        #10000;
        $finish;
    end

endmodule

chip8_top_tb.vcd
$date
	Sat Oct 18 05:15:22 2025
$end
$version
	Icarus Verilog
$end
$timescale
	1ps
$end
$scope module chip8_top_testbench $end
$var wire 2048 ! display [2047:0] $end
$var reg 1 " clock $end
$var reg 16 # key_pressed [15:0] $end
$var reg 1 $ reset $end
$scope module DUT $end
$var wire 1 " clk $end
$var wire 2048 % display [2047:0] $end
$var wire 16 & key_pressed [15:0] $end
$var wire 1 $ reset $end
$var wire 5 ' y [4:0] $end
$var wire 6 ( x [5:0] $end
$var wire 8 ) sprite_data [7:0] $end
$var wire 1 * mem_write $end
$var wire 1 + mem_read $end
$var wire 8 , mem_data_out [7:0] $end
$var wire 8 - mem_data_in [7:0] $end
$var wire 12 . mem_addr_out [11:0] $end
$var wire 4 / draw_row_index [3:0] $end
$var wire 1 0 draw $end
$var wire 2048 1 display_after [2047:0] $end
$var wire 1 2 collision $end
$var reg 2048 3 display_now [2047:0] $end
$scope module cpu $end
$var wire 1 " clk $end
$var wire 16 4 key_pressed [15:0] $end
$var wire 1 $ reset $end
$var wire 8 5 mem_data_out [7:0] $end
$var wire 1 2 collision $end
$var reg 12 6 I [11:0] $end
$var reg 8 7 delay_timer [7:0] $end
$var reg 1 0 draw $end
$var reg 4 8 draw_row [3:0] $end
$var reg 4 9 draw_row_index [3:0] $end
$var reg 4 : i [3:0] $end
$var reg 16 ; lfsr [15:0] $end
$var reg 12 < mem_addr_out [11:0] $end
$var reg 8 = mem_data_in [7:0] $end
$var reg 1 + mem_read $end
$var reg 1 * mem_write $end
$var reg 21 > one_hz [20:0] $end
$var reg 16 ? opcode [15:0] $end
$var reg 8 @ opcode_fh [7:0] $end
$var reg 8 A opcode_sh [7:0] $end
$var reg 12 B pc [11:0] $end
$var reg 4 C pc_data [3:0] $end
$var reg 8 D sound_timer [7:0] $end
$var reg 8 E sprite_data [7:0] $end
$var reg 4 F state [3:0] $end
$var reg 6 G x [5:0] $end
$var reg 5 H y [4:0] $end
$upscope $end
$scope module display_module $end
$var wire 1 " clk $end
$var wire 2048 I display_in [2047:0] $end
$var wire 1 0 draw $end
$var wire 1 $ reset $end
$var wire 4 J row_index [3:0] $end
$var wire 8 K sprite_data [7:0] $end
$var wire 6 L x [5:0] $end
$var wire 5 M y [4:0] $end
$var reg 1 N collide $end
$var reg 1 2 collision $end
$var reg 2048 O display_out [2047:0] $end
$var reg 2048 P next_display [2047:0] $end
$var integer 32 Q i [31:0] $end
$var integer 32 R index [31:0] $end
$upscope $end
$scope module mem $end
$var wire 1 " clk $end
$var wire 12 S mem_address [11:0] $end
$var wire 8 T mem_data_in [7:0] $end
$var wire 1 + read $end
$var wire 1 * write $end
$var reg 8 U mem_data_out [7:0] $end
$upscope $end
$upscope $end
$upscope $end
$enddefinitions $end
#0
$dumpvars
bx U
bx T
bx S
bx R
b1000 Q
b0 P
bx O
0N
bx M
bx L
b0 K
b0 J
b0 I
bx H
bx G
b0 F
b0 E
b0 D
b0 C
b1000000000 B
b0 A
b0 @
b0 ?
b0 >
bx =
bx <
b1010110011100001 ;
bx :
b0 9
b0 8
b0 7
b0 6
bx 5
b0 4
b0 3
x2
bx 1
00
b0 /
bx .
bx -
bx ,
0+
0*
b0 )
bx (
bx '
b0 &
b0 %
1$
b0 #
0"
b0 !
$end
#10000
b0 1
b0 O
02
1"
#20000
0"
0$
#30000
b1 F
1+
b1000000000 .
b1000000000 <
b1000000000 S
b101100111000010 ;
b1 >
1"
#40000
0"
#50000
b10 F
0+
b1011001110000100 ;
b10 >
b1100000 ,
b1100000 5
b1100000 U
1"
#60000
0"
#70000
b11 F
1+
b1000000001 .
b1000000001 <
b1000000001 S
b1100000 @
b110011100001000 ;
b11 >
1"
#80000
0"
#90000
b100 F
0+
b1100111000010000 ;
b100 >
b11100 ,
b11100 5
b11100 U
1"
#100000
0"
#110000
b110 F
b11100 A
b1001110000100000 ;
b101 >
1"
#120000
0"
#130000
b101 F
b110000000011100 ?
b11100001000000 ;
b110 >
1"
#140000
0"
#150000
b0 F
b1000000010 B
b111000010000000 ;
b111 >
1"
#160000
0"
#170000
b1 F
1+
b1000000010 .
b1000000010 <
b1000000010 S
b1110000100000000 ;
b1000 >
1"
#180000
0"
#190000
b10 F
0+
b1100001000000001 ;
b1001 >
b1100001 ,
b1100001 5
b1100001 U
1"
#200000
0"
#210000
b11 F
1+
b1000000011 .
b1000000011 <
b1000000011 S
b1100001 @
b1000010000000011 ;
b1010 >
1"
#220000
0"
#230000
b100 F
0+
b100000000111 ;
b1011 >
b1010 ,
b1010 5
b1010 U
1"
#240000
0"
#250000
b110 F
b1010 A
b1000000001111 ;
b1100 >
1"
#260000
0"
#270000
b101 F
b110000100001010 ?
b10000000011111 ;
b1101 >
1"
#280000
0"
#290000
b0 F
b1000000100 B
b100000000111110 ;
b1110 >
1"
#300000
0"
#310000
b1 F
1+
b1000000100 .
b1000000100 <
b1000000100 S
b1000000001111101 ;
b1111 >
1"
#320000
0"
#330000
b10 F
0+
b11111010 ;
b10000 >
b10100011 ,
b10100011 5
b10100011 U
1"
#340000
0"
#350000
b11 F
1+
b1000000101 .
b1000000101 <
b1000000101 S
b10100011 @
b111110100 ;
b10001 >
1"
#360000
0"
#370000
b100 F
0+
b1111101001 ;
b10010 >
b0 ,
b0 5
b0 U
1"
#380000
0"
#390000
b110 F
b0 A
b11111010011 ;
b10011 >
1"
#400000
0"
#410000
b101 F
b1010001100000000 ?
b111110100111 ;
b10100 >
1"
#420000
0"
#430000
b0 F
b1000000110 B
b1111101001110 ;
b10101 >
1"
#440000
0"
#450000
b1 F
1+
b1000000110 .
b1000000110 <
b1000000110 S
b11111010011101 ;
b10110 >
1"
#460000
0"
#470000
b10 F
0+
b111110100111010 ;
b10111 >
b11010000 ,
b11010000 5
b11010000 U
1"
#480000
0"
#490000
b11 F
1+
b1000000111 .
b1000000111 <
b1000000111 S
b11010000 @
b1111101001110100 ;
b11000 >
1"
#500000
0"
#510000
b100 F
0+
b1111010011101000 ;
b11001 >
b10101 ,
b10101 5
b10101 U
1"
#520000
0"
#530000
b110 F
b10101 A
b1110100111010000 ;
b11010 >
1"
#540000
0"
#550000
b101 F
b1101000000010101 ?
b1101001110100000 ;
b11011 >
1"
#560000
0"
#570000
b1010 F
b0 .
b0 <
b0 S
1+
b1010011101000000 ;
b11100 >
1"
#580000
0"
#590000
b1010100000000000000000000000000000000000000000000000000000000000000000000000000000000000000000000000000000000000000000000000000000000000000000000000000000000000000000000000000000000000000000000000000000000000000000000000000000000000000000000000000000000000000000000000000000000000000000000000000000000000000000000000000000000000000000000000000000000000000000000000000000000000000000000000000000000000000000000000000000000000000000000000000000000000000000000000000000000000000000000000000000000000000000000000000000000000000000000000000000000000000000000000000000000000000000000000000000000000000000000000000000000000000000000000000000000000000000000000000000000000000000000000 P
b1010100011 R
b1000 Q
b1011 F
b1010 '
b1010 H
b1010 M
b11100 (
b11100 G
b11100 L
b10101 )
b10101 E
b10101 K
10
0+
b100111010000001 ;
b11101 >
b11110000 ,
b11110000 5
b11110000 U
1"
#600000
0"
#610000
b1100 F
1+
b1 .
b1 <
b1 S
b1 8
00
b1001110100000010 ;
b11110 >
b1010100000000000000000000000000000000000000000000000000000000000000000000000000000000000000000000000000000000000000000000000000000000000000000000000000000000000000000000000000000000000000000000000000000000000000000000000000000000000000000000000000000000000000000000000000000000000000000000000000000000000000000000000000000000000000000000000000000000000000000000000000000000000000000000000000000000000000000000000000000000000000000000000000000000000000000000000000000000000000000000000000000000000000000000000000000000000000000000000000000000000000000000000000000000000000000000000000000000000000000000000000000000000000000000000000000000000000000000000000000000000000000000000 1
b1010100000000000000000000000000000000000000000000000000000000000000000000000000000000000000000000000000000000000000000000000000000000000000000000000000000000000000000000000000000000000000000000000000000000000000000000000000000000000000000000000000000000000000000000000000000000000000000000000000000000000000000000000000000000000000000000000000000000000000000000000000000000000000000000000000000000000000000000000000000000000000000000000000000000000000000000000000000000000000000000000000000000000000000000000000000000000000000000000000000000000000000000000000000000000000000000000000000000000000000000000000000000000000000000000000000000000000000000000000000000000000000000000 O
1"
#620000
0"
#630000
b1010 F
0+
b11101000000101 ;
b11111 >
b10010000 ,
b10010000 5
b10010000 U
1"
#640000
0"
#650000
b1011011111 R
b1000 Q
b1001000000000000000000000000000000000000000000000000000000000000000000000000000000000000000000000000000000000000000000000000000000000000000000000000000000000000000000000000000000000000000000000000000000000000000000000000000000000000000000000000000000000000000000000000000000000000000000000000000000000000000000000000000000000000000000000000000000000000000000000000000000000000000000000000000000000000000000000000000000000000000000000000000000000000000000000000000000000000000000000000000000000000000000000000000000000000000000000000000000000000000000000000000000000000000000000000000000000000000000000000000000000000000000000000000000000000000000000000000000000000000000000000000000000000000000000000000000000000000000000000000000000000 P
b1011 F
b1 /
b1 9
b1 J
b10010000 )
b10010000 E
b10010000 K
10
b111010000001011 ;
b100000 >
1"
#660000
0"
#670000
b1011011111 R
b1000 Q
b1001000000000000000000000000000000000000000000000000000000001010100000000000000000000000000000000000000000000000000000000000000000000000000000000000000000000000000000000000000000000000000000000000000000000000000000000000000000000000000000000000000000000000000000000000000000000000000000000000000000000000000000000000000000000000000000000000000000000000000000000000000000000000000000000000000000000000000000000000000000000000000000000000000000000000000000000000000000000000000000000000000000000000000000000000000000000000000000000000000000000000000000000000000000000000000000000000000000000000000000000000000000000000000000000000000000000000000000000000000000000000000000000000000000000000000000000000000000000000000000000000000000000000 P
b1100 F
1+
b10 .
b10 <
b10 S
b10 8
00
b1110100000010110 ;
b100001 >
b1010100000000000000000000000000000000000000000000000000000000000000000000000000000000000000000000000000000000000000000000000000000000000000000000000000000000000000000000000000000000000000000000000000000000000000000000000000000000000000000000000000000000000000000000000000000000000000000000000000000000000000000000000000000000000000000000000000000000000000000000000000000000000000000000000000000000000000000000000000000000000000000000000000000000000000000000000000000000000000000000000000000000000000000000000000000000000000000000000000000000000000000000000000000000000000000000000000000000000000000000000000000000000000000000000000000000000000000000000000000000000000000000000 !
b1010100000000000000000000000000000000000000000000000000000000000000000000000000000000000000000000000000000000000000000000000000000000000000000000000000000000000000000000000000000000000000000000000000000000000000000000000000000000000000000000000000000000000000000000000000000000000000000000000000000000000000000000000000000000000000000000000000000000000000000000000000000000000000000000000000000000000000000000000000000000000000000000000000000000000000000000000000000000000000000000000000000000000000000000000000000000000000000000000000000000000000000000000000000000000000000000000000000000000000000000000000000000000000000000000000000000000000000000000000000000000000000000000 %
b1010100000000000000000000000000000000000000000000000000000000000000000000000000000000000000000000000000000000000000000000000000000000000000000000000000000000000000000000000000000000000000000000000000000000000000000000000000000000000000000000000000000000000000000000000000000000000000000000000000000000000000000000000000000000000000000000000000000000000000000000000000000000000000000000000000000000000000000000000000000000000000000000000000000000000000000000000000000000000000000000000000000000000000000000000000000000000000000000000000000000000000000000000000000000000000000000000000000000000000000000000000000000000000000000000000000000000000000000000000000000000000000000000 3
b1010100000000000000000000000000000000000000000000000000000000000000000000000000000000000000000000000000000000000000000000000000000000000000000000000000000000000000000000000000000000000000000000000000000000000000000000000000000000000000000000000000000000000000000000000000000000000000000000000000000000000000000000000000000000000000000000000000000000000000000000000000000000000000000000000000000000000000000000000000000000000000000000000000000000000000000000000000000000000000000000000000000000000000000000000000000000000000000000000000000000000000000000000000000000000000000000000000000000000000000000000000000000000000000000000000000000000000000000000000000000000000000000000 I
b1001000000000000000000000000000000000000000000000000000000000000000000000000000000000000000000000000000000000000000000000000000000000000000000000000000000000000000000000000000000000000000000000000000000000000000000000000000000000000000000000000000000000000000000000000000000000000000000000000000000000000000000000000000000000000000000000000000000000000000000000000000000000000000000000000000000000000000000000000000000000000000000000000000000000000000000000000000000000000000000000000000000000000000000000000000000000000000000000000000000000000000000000000000000000000000000000000000000000000000000000000000000000000000000000000000000000000000000000000000000000000000000000000000000000000000000000000000000000000000000000000000000000000 1
b1001000000000000000000000000000000000000000000000000000000000000000000000000000000000000000000000000000000000000000000000000000000000000000000000000000000000000000000000000000000000000000000000000000000000000000000000000000000000000000000000000000000000000000000000000000000000000000000000000000000000000000000000000000000000000000000000000000000000000000000000000000000000000000000000000000000000000000000000000000000000000000000000000000000000000000000000000000000000000000000000000000000000000000000000000000000000000000000000000000000000000000000000000000000000000000000000000000000000000000000000000000000000000000000000000000000000000000000000000000000000000000000000000000000000000000000000000000000000000000000000000000000000000 O
1"
#680000
0"
#690000
b1010 F
0+
b1101000000101101 ;
b100010 >
1"
#700000
0"
#710000
b1100011111 R
b1000 Q
b10010000000000000000000000000000000000000000000000000000000000000000000000000000000000000000000000000000000000000000000000001010100000000000000000000000000000000000000000000000000000000000000000000000000000000000000000000000000000000000000000000000000000000000000000000000000000000000000000000000000000000000000000000000000000000000000000000000000000000000000000000000000000000000000000000000000000000000000000000000000000000000000000000000000000000000000000000000000000000000000000000000000000000000000000000000000000000000000000000000000000000000000000000000000000000000000000000000000000000000000000000000000000000000000000000000000000000000000000000000000000000000000000000000000000000000000000000000000000000000000000000000000000000000000000000000000000000000000000000000000000000000000000000000 P
b1011 F
b10 /
b10 9
b10 J
10
b1010000001011011 ;
b100011 >
1"
#720000
0"
#730000
b1100011111 R
b1000 Q
b10010000000000000000000000000000000000000000000000000000000000001001000000000000000000000000000000000000000000000000000000000000000000000000000000000000000000000000000000000000000000000000000000000000000000000000000000000000000000000000000000000000000000000000000000000000000000000000000000000000000000000000000000000000000000000000000000000000000000000000000000000000000000000000000000000000000000000000000000000000000000000000000000000000000000000000000000000000000000000000000000000000000000000000000000000000000000000000000000000000000000000000000000000000000000000000000000000000000000000000000000000000000000000000000000000000000000000000000000000000000000000000000000000000000000000000000000000000000000000000000000000000000000000000000000000000000000000000000000000000000000000000000000000000 P
b1001000000000000000000000000000000000000000000000000000000000000000000000000000000000000000000000000000000000000000000000000000000000000000000000000000000000000000000000000000000000000000000000000000000000000000000000000000000000000000000000000000000000000000000000000000000000000000000000000000000000000000000000000000000000000000000000000000000000000000000000000000000000000000000000000000000000000000000000000000000000000000000000000000000000000000000000000000000000000000000000000000000000000000000000000000000000000000000000000000000000000000000000000000000000000000000000000000000000000000000000000000000000000000000000000000000000000000000000000000000000000000000000000000000000000000000000000000000000000000000000000000000000000 !
b1001000000000000000000000000000000000000000000000000000000000000000000000000000000000000000000000000000000000000000000000000000000000000000000000000000000000000000000000000000000000000000000000000000000000000000000000000000000000000000000000000000000000000000000000000000000000000000000000000000000000000000000000000000000000000000000000000000000000000000000000000000000000000000000000000000000000000000000000000000000000000000000000000000000000000000000000000000000000000000000000000000000000000000000000000000000000000000000000000000000000000000000000000000000000000000000000000000000000000000000000000000000000000000000000000000000000000000000000000000000000000000000000000000000000000000000000000000000000000000000000000000000000000 %
b1001000000000000000000000000000000000000000000000000000000000000000000000000000000000000000000000000000000000000000000000000000000000000000000000000000000000000000000000000000000000000000000000000000000000000000000000000000000000000000000000000000000000000000000000000000000000000000000000000000000000000000000000000000000000000000000000000000000000000000000000000000000000000000000000000000000000000000000000000000000000000000000000000000000000000000000000000000000000000000000000000000000000000000000000000000000000000000000000000000000000000000000000000000000000000000000000000000000000000000000000000000000000000000000000000000000000000000000000000000000000000000000000000000000000000000000000000000000000000000000000000000000000000 3
b1001000000000000000000000000000000000000000000000000000000000000000000000000000000000000000000000000000000000000000000000000000000000000000000000000000000000000000000000000000000000000000000000000000000000000000000000000000000000000000000000000000000000000000000000000000000000000000000000000000000000000000000000000000000000000000000000000000000000000000000000000000000000000000000000000000000000000000000000000000000000000000000000000000000000000000000000000000000000000000000000000000000000000000000000000000000000000000000000000000000000000000000000000000000000000000000000000000000000000000000000000000000000000000000000000000000000000000000000000000000000000000000000000000000000000000000000000000000000000000000000000000000000000 I
b1100 F
1+
b11 .
b11 <
b11 S
b11 8
00
b100000010110110 ;
b100100 >
b10010000000000000000000000000000000000000000000000000000000000000000000000000000000000000000000000000000000000000000000000001010100000000000000000000000000000000000000000000000000000000000000000000000000000000000000000000000000000000000000000000000000000000000000000000000000000000000000000000000000000000000000000000000000000000000000000000000000000000000000000000000000000000000000000000000000000000000000000000000000000000000000000000000000000000000000000000000000000000000000000000000000000000000000000000000000000000000000000000000000000000000000000000000000000000000000000000000000000000000000000000000000000000000000000000000000000000000000000000000000000000000000000000000000000000000000000000000000000000000000000000000000000000000000000000000000000000000000000000000000000000000000000000000 1
b10010000000000000000000000000000000000000000000000000000000000000000000000000000000000000000000000000000000000000000000000001010100000000000000000000000000000000000000000000000000000000000000000000000000000000000000000000000000000000000000000000000000000000000000000000000000000000000000000000000000000000000000000000000000000000000000000000000000000000000000000000000000000000000000000000000000000000000000000000000000000000000000000000000000000000000000000000000000000000000000000000000000000000000000000000000000000000000000000000000000000000000000000000000000000000000000000000000000000000000000000000000000000000000000000000000000000000000000000000000000000000000000000000000000000000000000000000000000000000000000000000000000000000000000000000000000000000000000000000000000000000000000000000000 O
1"
#740000
0"
#750000
b1010 F
0+
b1000000101101101 ;
b100101 >
1"
#760000
0"
#770000
b1101011111 R
b1000 Q
b100100000000000000000000000000000000000000000000000000000000000000000000000000000000000000000000000000000000000000000000000000001001000000000000000000000000000000000000000000000000000000000000000000000000000000000000000000000000000000000000000000000000000000000000000000000000000000000000000000000000000000000000000000000000000000000000000000000000000000000000000000000000000000000000000000000000000000000000000000000000000000000000000000000000000000000000000000000000000000000000000000000000000000000000000000000000000000000000000000000000000000000000000000000000000000000000000000000000000000000000000000000000000000000000000000000000000000000000000000000000000000000000000000000000000000000000000000000000000000000000000000000000000000000000000000000000000000000000000000000000000000000000000000000000000000000000000000000000000000000000000000000000000000000000 P
b1011 F
b11 /
b11 9
b11 J
10
b1011011011 ;
b100110 >
1"
#780000
0"
